[
    {
        "english_name": "Minsk",
        "arabic_name": "مينسك"
    },
    {
        "english_name": "Homyel'",
        "arabic_name": "غوميل"
    },
    {
        "english_name": "Hrodna",
        "arabic_name": "غرودنو"
    },
    {
        "english_name": "Vitsyebsk",
        "arabic_name": "فيتيبسك"
    },
    {
        "english_name": "Mahilyow",
        "arabic_name": "موجيلوف"
    },
    {
        "english_name": "Brest",
        "arabic_name": "بريست"
    },
    {
        "english_name": "Babruysk",
        "arabic_name": "بابرويسك"
    },
    {
        "english_name": "Baranavichy",
        "arabic_name": "بارانافيتشي"
    },
    {
        "english_name": "Pinsk",
        "arabic_name": "بينسك"
    },
    {
        "english_name": "Mazyr",
        "arabic_name": "مازير"
    },
    {
        "english_name": "Lida",
        "arabic_name": "ليدا"
    },
    {
        "english_name": "Orsha",
        "arabic_name": "أورشا"
    },
    {
        "english_name": "Salihorsk",
        "arabic_name": "ساليهورسك"
    },
    {
        "english_name": "Maladzyechna",
        "arabic_name": "مالادزيشنا"
    },
    {
        "english_name": "Polatsk",
        "arabic_name": "بولوتسك"
    },
    {
        "english_name": "Zhlobin",
        "arabic_name": "جلوبين"
    },
    {
        "english_name": "Slutsk",
        "arabic_name": "سلوتسك"
    },
    {
        "english_name": "Kobryn",
        "arabic_name": "كوبرين"
    },
    {
        "english_name": "Slonim",
        "arabic_name": "سلونيم"
    },
    {
        "english_name": "Vawkavysk",
        "arabic_name": "فاوكافيسك"
    },
    {
        "english_name": "Dzyarzhynsk",
        "arabic_name": "دزيارجينسك"
    },
    {
        "english_name": "Asipovichy",
        "arabic_name": "أسيبوفيتشي"
    },
    {
        "english_name": "Horki",
        "arabic_name": "هوركي"
    },
    {
        "english_name": "Khoyniki",
        "arabic_name": "خوينيكي"
    },
    {
        "english_name": "Baran",
        "arabic_name": "باران"
    },
    {
        "english_name": "Chachersk",
        "arabic_name": "تشاتشيرسك"
    }
]